co_deployer/__init__.py
co_deployer/co_deployer.py
co_deployer/modules/Cmd.py
co_deployer/modules/Config.py
co_deployer/modules/Deploy.py
co_deployer/modules/Ftp.py
co_deployer/modules/Sftp.py
co_deployer/modules/Ssh.py
co_deployer/modules/__init__.py
co_deployer-1.0.4.dist-info/METADATA
co_deployer-1.0.4.dist-info/WHEEL
co_deployer-1.0.4.dist-info/entry_points.txt
co_deployer-1.0.4.dist-info/top_level.txt
co_deployer-1.0.4.dist-info/RECORD
