Metadata-Version: 2.1
Name: co-deployer
Version: 1.0.4
Summary: A simple deployment tool for your projects
Author: Elwan Mayencourt
Requires-Dist: rich
Requires-Dist: paramiko
Requires-Dist: jsonschema
